evermemos/__init__.py
evermemos/_base_client.py
evermemos/_client.py
evermemos/_compat.py
evermemos/_constants.py
evermemos/_exceptions.py
evermemos/_files.py
evermemos/_models.py
evermemos/_qs.py
evermemos/_resource.py
evermemos/_response.py
evermemos/_streaming.py
evermemos/_types.py
evermemos/_version.py
evermemos/py.typed
evermemos/_utils/__init__.py
evermemos/_utils/_compat.py
evermemos/_utils/_datetime_parse.py
evermemos/_utils/_json.py
evermemos/_utils/_logs.py
evermemos/_utils/_proxy.py
evermemos/_utils/_reflection.py
evermemos/_utils/_resources_proxy.py
evermemos/_utils/_streams.py
evermemos/_utils/_sync.py
evermemos/_utils/_transform.py
evermemos/_utils/_typing.py
evermemos/_utils/_utils.py
evermemos/lib/.keep
evermemos/resources/__init__.py
evermemos/resources/v1/__init__.py
evermemos/resources/v1/v1.py
evermemos/resources/v1/memories/__init__.py
evermemos/resources/v1/memories/conversation_meta.py
evermemos/resources/v1/memories/memories.py
evermemos/resources/v1/status/__init__.py
evermemos/resources/v1/status/request.py
evermemos/resources/v1/status/status.py
evermemos/types/__init__.py
evermemos/types/v1/__init__.py
evermemos/types/v1/memory_add_params.py
evermemos/types/v1/memory_add_response.py
evermemos/types/v1/memory_delete_params.py
evermemos/types/v1/memory_delete_response.py
evermemos/types/v1/memory_get_response.py
evermemos/types/v1/memory_search_response.py
evermemos/types/v1/memory_type.py
evermemos/types/v1/metadata.py
evermemos/types/v1/memories/__init__.py
evermemos/types/v1/memories/conversation_meta_create_params.py
evermemos/types/v1/memories/conversation_meta_create_response.py
evermemos/types/v1/memories/conversation_meta_get_response.py
evermemos/types/v1/memories/conversation_meta_update_params.py
evermemos/types/v1/memories/conversation_meta_update_response.py
evermemos/types/v1/status/__init__.py
evermemos/types/v1/status/request_get_params.py
evermemos/types/v1/status/request_get_response.py
evermemos-0.3.10.dist-info/METADATA
evermemos-0.3.10.dist-info/WHEEL
evermemos-0.3.10.dist-info/licenses/LICENSE
evermemos-0.3.10.dist-info/RECORD
